jupyter_firefly_extensions/__init__.py
jupyter_firefly_extensions/_version.py
jupyter_firefly_extensions/handlers.py
jupyter_firefly_extensions/labextension/package.json
jupyter_firefly_extensions/labextension/static/486.54c6ff21b2c0db7e9965.js
jupyter_firefly_extensions/labextension/static/486.54c6ff21b2c0db7e9965.js.LICENSE.txt
jupyter_firefly_extensions/labextension/static/575.9f26a0781e446d102b95.js
jupyter_firefly_extensions/labextension/static/743.f39a350fe006bcabddda.js
jupyter_firefly_extensions/labextension/static/747.364f80cac17ab77519ab.js
jupyter_firefly_extensions/labextension/static/773.2b45d8643eab1b6782ed.js
jupyter_firefly_extensions/labextension/static/remoteEntry.72f9abd938f52af6dba2.js
jupyter_firefly_extensions/labextension/static/style.js
jupyter_firefly_extensions/labextension/static/third-party-licenses.json
jupyter_firefly_extensions/tests/__init__.py
jupyter_firefly_extensions/tests/test_handlers.py
jupyter_firefly_extensions-4.5.1.data/data/etc/jupyter/jupyter_server_config.d/jupyter_firefly_extensions.json
jupyter_firefly_extensions-4.5.1.data/data/share/jupyter/labextensions/jupyter_firefly_extensions/package.json
jupyter_firefly_extensions-4.5.1.data/data/share/jupyter/labextensions/jupyter_firefly_extensions/static/486.54c6ff21b2c0db7e9965.js
jupyter_firefly_extensions-4.5.1.data/data/share/jupyter/labextensions/jupyter_firefly_extensions/static/486.54c6ff21b2c0db7e9965.js.LICENSE.txt
jupyter_firefly_extensions-4.5.1.data/data/share/jupyter/labextensions/jupyter_firefly_extensions/static/575.9f26a0781e446d102b95.js
jupyter_firefly_extensions-4.5.1.data/data/share/jupyter/labextensions/jupyter_firefly_extensions/static/743.f39a350fe006bcabddda.js
jupyter_firefly_extensions-4.5.1.data/data/share/jupyter/labextensions/jupyter_firefly_extensions/static/747.364f80cac17ab77519ab.js
jupyter_firefly_extensions-4.5.1.data/data/share/jupyter/labextensions/jupyter_firefly_extensions/static/773.2b45d8643eab1b6782ed.js
jupyter_firefly_extensions-4.5.1.dist-info/METADATA
jupyter_firefly_extensions-4.5.1.dist-info/WHEEL
jupyter_firefly_extensions-4.5.1.dist-info/RECORD
