Metadata-Version: 2.4
Name: jupyter_firefly_extensions
Version: 4.5.1
Dynamic: Keywords
Summary: Jupyterlab extensions for rendering FITS and displaying tables, images, & charts with Firefly
Project-URL: Homepage, https://github.com/Caltech-IPAC/jupyter_firefly_extensions
Project-URL: Bug Tracker, https://github.com/Caltech-IPAC/jupyter_firefly_extensions/issues
Project-URL: Repository, https://github.com/Caltech-IPAC/jupyter_firefly_extensions.git
Author-email: IPAC Firefly Developers <roby@ipac.caltech.edu>
License: BSD-3-Clause License
Classifier: Framework :: Jupyter
Classifier: Framework :: Jupyter :: JupyterLab
Classifier: Framework :: Jupyter :: JupyterLab :: 4
Classifier: Framework :: Jupyter :: JupyterLab :: Extensions
Classifier: Framework :: Jupyter :: JupyterLab :: Extensions :: Prebuilt
Classifier: Intended Audience :: Developers
Classifier: Intended Audience :: Science/Research
Classifier: Intended Audience :: System Administrators
Classifier: License :: OSI Approved :: BSD License
Classifier: Programming Language :: Python
Classifier: Programming Language :: Python :: 3
Requires-Python: >=3.10
Requires-Dist: firefly-client>=3.3.0
Requires-Dist: jupyter-server<3,>=2.0.1
Provides-Extra: test
Requires-Dist: coverage; extra == 'test'
Requires-Dist: pytest; extra == 'test'
Requires-Dist: pytest-asyncio; extra == 'test'
Requires-Dist: pytest-cov; extra == 'test'
Requires-Dist: pytest-jupyter[server]>=0.6.0; extra == 'test'
